Metadata-Version: 2.4
Name: ether-lite
Version: 2025.1.2a1
Summary: Developer focused framework for building distributed data acquisition and analysis systems.
Project-URL: Homepage, https://github.com/shababo/ether
Project-URL: Issues, https://github.com/shababo/ether/issues
Author-email: Shababo <benshababo@gmail.com>
License-File: LICENSE
Requires-Python: >=3.10
Requires-Dist: airtable[webapp]>=0.4.8
Requires-Dist: click>=8.1.7
Requires-Dist: ether-python[airtable,all,webapp]>=2025.1.2a1
Requires-Dist: pandas>=2.2.3
Requires-Dist: psutil>=6.1.0
Requires-Dist: pydantic>=2.9.2
Requires-Dist: pyyaml>=6.0.2
Requires-Dist: pyzmq>=26.2.0
Requires-Dist: redis>=5.2.0
Requires-Dist: requests>=2.32.3
Requires-Dist: sqlalchemy>=2.0.36
Provides-Extra: integrations-airtable
Requires-Dist: pyairtable>=1.1.0; extra == 'integrations-airtable'
Provides-Extra: integrations-base
Requires-Dist: pyserial>=3.5; extra == 'integrations-base'
Provides-Extra: integrations-oephys
Requires-Dist: open-ephys-python-tools>=0.1.12; extra == 'integrations-oephys'
Provides-Extra: webapp
Requires-Dist: dash-ag-grid>=31.3.0; extra == 'webapp'
Requires-Dist: dash-iconify>=0.1.2; extra == 'webapp'
Requires-Dist: dash-lumino-components>=0.0.20; extra == 'webapp'
Requires-Dist: dash-mantine-components>=0.15.1; extra == 'webapp'
Requires-Dist: dash>=2.18.2; extra == 'webapp'
